{"is_source_file": true, "format": "TypeScript/TSX", "description": "React functional component for the 'Production' page, providing a simple UI with a header and description text.", "external_files": ["@mui/material", "react"], "external_methods": ["React.FC", "Box", "Typography"], "published": ["Production"], "classes": [], "methods": [{"name": "Production", "description": "React functional component rendering the Production page."}], "calls": ["React", "Box", "Typography"], "search-terms": ["Production", "React.FC", "TypeScript", "tsx", "Material UI", "Page component"], "state": 2, "file_id": 16, "knowledge_revision": 36, "git_revision": "", "ctags": [], "hash": "948fb31e0d7e2c877310c2e27bfc4f12", "format-version": 4, "code-base-name": "manufacturing_frontend", "filename": "manufacturing_frontend/src/pages/Production.tsx", "revision_history": [{"36": ""}]}